pycristoforo/__init__.py
pycristoforo/geo/__init__.py
pycristoforo/geo/countries.py
pycristoforo/geo/eucountries.py
pycristoforo/geo/key_value_pair.py
pycristoforo/geo/shape.py
pycristoforo/resources/__init__.py
pycristoforo/resources/countries.geojson
pycristoforo/resources/eu_countries.json
pycristoforo/tests/__init__.py
pycristoforo/tests/conftest.py
pycristoforo/tests/test_skeleton.py
pycristoforo/utils/__init__.py
pycristoforo/utils/constants.py
pycristoforo/utils/utils.py
PyCristoforo-2.0.0.dist-info/AUTHORS.rst
PyCristoforo-2.0.0.dist-info/LICENSE.txt
PyCristoforo-2.0.0.dist-info/METADATA
PyCristoforo-2.0.0.dist-info/WHEEL
PyCristoforo-2.0.0.dist-info/top_level.txt
PyCristoforo-2.0.0.dist-info/RECORD
