Metadata-Version: 2.1
Name: PyCristoforo
Version: 2.0.0
Summary: Python library for the generation of contestualized random coordinates
Home-page: https://github.com/AleNegrini/PyCristoforo
Author: Alessandro
Author-email: alessandro2.negrini@gmail.com
License: UNKNOWN
Platform: UNKNOWN
Classifier: Programming Language :: Python :: 3
Classifier: License :: OSI Approved :: MIT License
Classifier: Operating System :: OS Independent
